{
  "match": {
    "matchId": 99000096,
    "label": "FCSB vs Petrolul Ploiesti",
    "date": "2026-05-13T17:30:00+03:00",
    "status": "played",
    "venue": "Rapid-Giulesti",
    "teams": [
      {
        "teamId": 9020,
        "teamName": "FCSB",
        "formation": "4-3-3"
      },
      {
        "teamId": 9017,
        "teamName": "Farul Constanta",
        "formation": "4-3-3"
      }
    ],
    "teamScope": "FCSB"
  },
  "summary": {
    "actionsAnalyzed": 307,
    "playersAnalyzed": 11,
    "averageDecisionValue": 0.209287,
    "lowDecisionPhases": 53,
    "phasesWithAlternative": 15,
    "missedShotOrGoalOpportunities": 7,
    "lowScoreThresholdUsed": 0.161764
  },
  "players": {
    "needsSupport": [
      {
        "player_id": "1007",
        "player_name": "L. Cristea",
        "decisionScore": 0.1946,
        "actionsAnalyzed": 18,
        "lowScoreActions": 11,
        "suggestedActions": 0,
        "avgPotentialGainOnSuggestions": 0.0589,
        "recommendedDecisionTypeWhenLow": null,
        "bestDecisionType": "carry",
        "weakDecisionType": "carry",
        "needsDecisionSupport": true
      },
      {
        "player_id": "1003",
        "player_name": "M. Thiam",
        "decisionScore": 0.1762,
        "actionsAnalyzed": 26,
        "lowScoreActions": 16,
        "suggestedActions": 2,
        "avgPotentialGainOnSuggestions": 0.0272,
        "recommendedDecisionTypeWhenLow": "pass",
        "bestDecisionType": "carry",
        "weakDecisionType": "pass",
        "needsDecisionSupport": true
      },
      {
        "player_id": "1001",
        "player_name": "A. Miron",
        "decisionScore": 0.1698,
        "actionsAnalyzed": 34,
        "lowScoreActions": 20,
        "suggestedActions": 1,
        "avgPotentialGainOnSuggestions": 0.0267,
        "recommendedDecisionTypeWhenLow": "pass",
        "bestDecisionType": "shot",
        "weakDecisionType": "shot",
        "needsDecisionSupport": true
      }
    ]
  },
  "phases": {
    "improvablePhases": [
      {
        "event_id": 880092017,
        "minute": 22,
        "second": 32,
        "player_name": "D. Oancea",
        "team_name": "TeamScope",
        "decision": "carry",
        "decisionValue": 0.1427,
        "bestDecisionType": "shot",
        "bestDecisionValue": 0.21,
        "potentialGain": 0.0673,
        "suggestedAlternative": "carry",
        "label": 0,
        "actualShotOnTarget": false,
        "actualGoal": true
      },
      {
        "event_id": 880068164,
        "minute": 5,
        "second": 21,
        "player_name": "A. Chipciu",
        "team_name": "TeamScope",
        "decision": "carry",
        "decisionValue": 0.2216,
        "bestDecisionType": "carry",
        "bestDecisionValue": 0.2815,
        "potentialGain": 0.0599,
        "suggestedAlternative": "pass",
        "label": 0,
        "actualShotOnTarget": true,
        "actualGoal": false
      },
      {
        "event_id": 880085757,
        "minute": 72,
        "second": 24,
        "player_name": "L. Cristea",
        "team_name": "TeamScope",
        "decision": "carry",
        "decisionValue": 0.2212,
        "bestDecisionType": "carry",
        "bestDecisionValue": 0.288,
        "potentialGain": 0.0668,
        "suggestedAlternative": "carry",
        "label": 1,
        "actualShotOnTarget": false,
        "actualGoal": false
      },
      {
        "event_id": 880001559,
        "minute": 45,
        "second": 42,
        "player_name": "A. Miron",
        "team_name": "TeamScope",
        "decision": "pass",
        "decisionValue": 0.1762,
        "bestDecisionType": "carry",
        "bestDecisionValue": 0.2084,
        "potentialGain": 0.0322,
        "suggestedAlternative": "carry",
        "label": 0,
        "actualShotOnTarget": false,
        "actualGoal": false
      },
      {
        "event_id": 880052329,
        "minute": 69,
        "second": 31,
        "player_name": "D. Oancea",
        "team_name": "TeamScope",
        "decision": "pass",
        "decisionValue": 0.262,
        "bestDecisionType": "carry",
        "bestDecisionValue": 0.2843,
        "potentialGain": 0.0222,
        "suggestedAlternative": "carry",
        "label": 0,
        "actualShotOnTarget": true,
        "actualGoal": false
      },
      {
        "event_id": 880091674,
        "minute": 70,
        "second": 37,
        "player_name": "O. Bic",
        "team_name": "TeamScope",
        "decision": "carry",
        "decisionValue": 0.2609,
        "bestDecisionType": "carry",
        "bestDecisionValue": 0.2931,
        "potentialGain": 0.0322,
        "suggestedAlternative": "shot",
        "label": 0,
        "actualShotOnTarget": false,
        "actualGoal": false
      },
      {
        "event_id": 880056577,
        "minute": 4,
        "second": 2,
        "player_name": "I. Stoica",
        "team_name": "TeamScope",
        "decision": "shot",
        "decisionValue": 0.2143,
        "bestDecisionType": "carry",
        "bestDecisionValue": 0.2798,
        "potentialGain": 0.0655,
        "suggestedAlternative": "shot",
        "label": 0,
        "actualShotOnTarget": false,
        "actualGoal": false
      },
      {
        "event_id": 880077088,
        "minute": 58,
        "second": 44,
        "player_name": "O. Bic",
        "team_name": "TeamScope",
        "decision": "pass",
        "decisionValue": 0.1254,
        "bestDecisionType": "carry",
        "bestDecisionValue": 0.1965,
        "potentialGain": 0.0711,
        "suggestedAlternative": "pass",
        "label": 0,
        "actualShotOnTarget": false,
        "actualGoal": false
      },
      {
        "event_id": 880022730,
        "minute": 59,
        "second": 51,
        "player_name": "O. Bic",
        "team_name": "TeamScope",
        "decision": "shot",
        "decisionValue": 0.1445,
        "bestDecisionType": "pass",
        "bestDecisionValue": 0.2128,
        "potentialGain": 0.0683,
        "suggestedAlternative": "carry",
        "label": 1,
        "actualShotOnTarget": false,
        "actualGoal": true
      },
      {
        "event_id": 880021006,
        "minute": 15,
        "second": 12,
        "player_name": "D. Oancea",
        "team_name": "TeamScope",
        "decision": "shot",
        "decisionValue": 0.2576,
        "bestDecisionType": "carry",
        "bestDecisionValue": 0.2977,
        "potentialGain": 0.0401,
        "suggestedAlternative": "carry",
        "label": 0,
        "actualShotOnTarget": false,
        "actualGoal": false
      },
      {
        "event_id": 880091838,
        "minute": 56,
        "second": 49,
        "player_name": "V. Gheorghe",
        "team_name": "TeamScope",
        "decision": "pass",
        "decisionValue": 0.1937,
        "bestDecisionType": "carry",
        "bestDecisionValue": 0.2216,
        "potentialGain": 0.0279,
        "suggestedAlternative": "pass",
        "label": 0,
        "actualShotOnTarget": true,
        "actualGoal": false
      },
      {
        "event_id": 880059036,
        "minute": 6,
        "second": 47,
        "player_name": "V. Gheorghe",
        "team_name": "TeamScope",
        "decision": "carry",
        "decisionValue": 0.2444,
        "bestDecisionType": "shot",
        "bestDecisionValue": 0.283,
        "potentialGain": 0.0385,
        "suggestedAlternative": "shot",
        "label": 0,
        "actualShotOnTarget": true,
        "actualGoal": true
      },
      {
        "event_id": 880094542,
        "minute": 57,
        "second": 4,
        "player_name": "A. Chipciu",
        "team_name": "TeamScope",
        "decision": "carry",
        "decisionValue": 0.1923,
        "bestDecisionType": "shot",
        "bestDecisionValue": 0.2563,
        "potentialGain": 0.064,
        "suggestedAlternative": "shot",
        "label": 1,
        "actualShotOnTarget": true,
        "actualGoal": false
      },
      {
        "event_id": 880072688,
        "minute": 86,
        "second": 48,
        "player_name": "L. Cristea",
        "team_name": "TeamScope",
        "decision": "pass",
        "decisionValue": 0.207,
        "bestDecisionType": "shot",
        "bestDecisionValue": 0.2811,
        "potentialGain": 0.0741,
        "suggestedAlternative": "shot",
        "label": 0,
        "actualShotOnTarget": true,
        "actualGoal": false
      },
      {
        "event_id": 880032833,
        "minute": 2,
        "second": 46,
        "player_name": "A. Miron",
        "team_name": "TeamScope",
        "decision": "shot",
        "decisionValue": 0.1769,
        "bestDecisionType": "pass",
        "bestDecisionValue": 0.247,
        "potentialGain": 0.0702,
        "suggestedAlternative": "shot",
        "label": 0,
        "actualShotOnTarget": false,
        "actualGoal": true
      },
      {
        "event_id": 880071731,
        "minute": 16,
        "second": 17,
        "player_name": "V. Gheorghe",
        "team_name": "TeamScope",
        "decision": "pass",
        "decisionValue": 0.2475,
        "bestDecisionType": "pass",
        "bestDecisionValue": 0.2892,
        "potentialGain": 0.0418,
        "suggestedAlternative": "pass",
        "label": 0,
        "actualShotOnTarget": false,
        "actualGoal": true
      },
      {
        "event_id": 880097234,
        "minute": 15,
        "second": 44,
        "player_name": "O. Bic",
        "team_name": "TeamScope",
        "decision": "pass",
        "decisionValue": 0.2678,
        "bestDecisionType": "shot",
        "bestDecisionValue": 0.3003,
        "potentialGain": 0.0326,
        "suggestedAlternative": "pass",
        "label": 1,
        "actualShotOnTarget": false,
        "actualGoal": false
      }
    ],
    "missedShotOrGoalOpportunities": [
      {
        "event_id": 880086252,
        "minute": 56,
        "second": 51,
        "player_name": "D. Oancea",
        "team_name": "TeamScope",
        "decision": "carry",
        "decisionValue": 0.3723,
        "bestDecisionType": "shot",
        "bestDecisionValue": 0.413,
        "potentialGain": 0.0407,
        "suggestedAlternative": null,
        "label": 0,
        "actualShotOnTarget": true,
        "actualGoal": true
      },
      {
        "event_id": 880092067,
        "minute": 54,
        "second": 36,
        "player_name": "D. Nistor",
        "team_name": "TeamScope",
        "decision": "pass",
        "decisionValue": 0.3799,
        "bestDecisionType": "carry",
        "bestDecisionValue": 0.4038,
        "potentialGain": 0.0239,
        "suggestedAlternative": null,
        "label": 0,
        "actualShotOnTarget": true,
        "actualGoal": false
      },
      {
        "event_id": 880038191,
        "minute": 56,
        "second": 28,
        "player_name": "D. Popa",
        "team_name": "TeamScope",
        "decision": "pass",
        "decisionValue": 0.2289,
        "bestDecisionType": "carry",
        "bestDecisionValue": 0.2871,
        "potentialGain": 0.0582,
        "suggestedAlternative": null,
        "label": 0,
        "actualShotOnTarget": true,
        "actualGoal": true
      },
      {
        "event_id": 880074284,
        "minute": 68,
        "second": 55,
        "player_name": "M. Thiam",
        "team_name": "TeamScope",
        "decision": "shot",
        "decisionValue": 0.3234,
        "bestDecisionType": "carry",
        "bestDecisionValue": 0.3725,
        "potentialGain": 0.0491,
        "suggestedAlternative": null,
        "label": 0,
        "actualShotOnTarget": true,
        "actualGoal": false
      },
      {
        "event_id": 880034632,
        "minute": 75,
        "second": 57,
        "player_name": "O. Bic",
        "team_name": "TeamScope",
        "decision": "carry",
        "decisionValue": 0.3119,
        "bestDecisionType": "shot",
        "bestDecisionValue": 0.3648,
        "potentialGain": 0.0529,
        "suggestedAlternative": null,
        "label": 0,
        "actualShotOnTarget": true,
        "actualGoal": false
      },
      {
        "event_id": 880032172,
        "minute": 29,
        "second": 5,
        "player_name": "D. Nistor",
        "team_name": "TeamScope",
        "decision": "pass",
        "decisionValue": 0.3552,
        "bestDecisionType": "shot",
        "bestDecisionValue": 0.3811,
        "potentialGain": 0.0259,
        "suggestedAlternative": null,
        "label": 1,
        "actualShotOnTarget": false,
        "actualGoal": false
      },
      {
        "event_id": 880015826,
        "minute": 54,
        "second": 25,
        "player_name": "O. Bic",
        "team_name": "TeamScope",
        "decision": "shot",
        "decisionValue": 0.2637,
        "bestDecisionType": "carry",
        "bestDecisionValue": 0.3123,
        "potentialGain": 0.0486,
        "suggestedAlternative": null,
        "label": 0,
        "actualShotOnTarget": true,
        "actualGoal": true
      }
    ]
  },
  "teamStats": {
    "decisionByType": [
      {
        "decision": "pass",
        "actions": 171,
        "avgDecisionValue": 0.2874,
        "avgPotentialGain": 0.0106,
        "lowDecisionPhases": 44
      },
      {
        "decision": "carry",
        "actions": 27,
        "avgDecisionValue": 0.1994,
        "avgPotentialGain": 0.0155,
        "lowDecisionPhases": 9
      },
      {
        "decision": "shot",
        "actions": 70,
        "avgDecisionValue": 0.1978,
        "avgPotentialGain": 0.0118,
        "lowDecisionPhases": 8
      }
    ],
    "timeline": [
      {
        "actions": 42,
        "avgDecisionValue": 0.1647,
        "lowDecisionPhases": 10,
        "phasesWithAlternative": 1,
        "minuteBucket": "0-14"
      },
      {
        "actions": 66,
        "avgDecisionValue": 0.2448,
        "lowDecisionPhases": 13,
        "phasesWithAlternative": 2,
        "minuteBucket": "15-29"
      },
      {
        "actions": 32,
        "avgDecisionValue": 0.2553,
        "lowDecisionPhases": 6,
        "phasesWithAlternative": 6,
        "minuteBucket": "30-44"
      },
      {
        "actions": 28,
        "avgDecisionValue": 0.2616,
        "lowDecisionPhases": 4,
        "phasesWithAlternative": 3,
        "minuteBucket": "45-59"
      },
      {
        "actions": 29,
        "avgDecisionValue": 0.2792,
        "lowDecisionPhases": 18,
        "phasesWithAlternative": 5,
        "minuteBucket": "60-74"
      },
      {
        "actions": 55,
        "avgDecisionValue": 0.2701,
        "lowDecisionPhases": 10,
        "phasesWithAlternative": 2,
        "minuteBucket": "75-89"
      },
      {
        "actions": 26,
        "avgDecisionValue": 0.27,
        "lowDecisionPhases": 10,
        "phasesWithAlternative": 0,
        "minuteBucket": "90-104"
      }
    ]
  }
}